dcscaffold/__init__.py
dcscaffold/libdcs.py
dcscaffold-0.1.0.dist-info/LICENSE
dcscaffold-0.1.0.dist-info/METADATA
dcscaffold-0.1.0.dist-info/WHEEL
dcscaffold-0.1.0.dist-info/top_level.txt
dcscaffold-0.1.0.dist-info/RECORD
