Metadata-Version: 2.1
Name: dcscaffold
Version: 0.1.0
Summary: Package used to scaffold a project using docker-compose
Home-page: https://github.com/egyanamtech/dcscaffold
Author: Mrityunjay Saxena
Author-email: mrityunjaysaxena1996@gmail.com
License: UNKNOWN
Project-URL: Bug Tracker, https://github.com/egyanamtech/dcscaffold/issues
Platform: UNKNOWN
Classifier: Programming Language :: Python :: 3
Classifier: License :: OSI Approved :: MIT License
Classifier: Operating System :: OS Independent
Requires-Python: >=3.6
License-File: LICENSE
